{
    "id": "ziye.shuqiapp.sub",
    "name": "ziye 书旗专用订阅",
    "author": "@ZIYE",
    "icon": "https://cdn.jsdelivr.net/gh/ziye888/JavaScript@main/ziye.png",
    "repo": "https://github.com/ziye888",
    "apps": [{
        "id": "shuqiappsss",
        "name": "书旗小说APP",
        "keys": ["shuqicjbody", "shuqisprwurl", "shuqiqdbody", "shuqijsqdbody", "shuqisyzjurl", "shuqitxjlbody", "shuqicjbody2",  "shuqisprwurl2", "shuqiqdbody2", "shuqijsqdbody2", "shuqisyzjurl2", "shuqitxjlbody2", "shuqicjbody3",  "shuqisprwurl3", "shuqiqdbody3", "shuqijsqdbody3", "shuqisyzjurl3", "shuqitxjlbody3", "shuqicjbody4",  "shuqisprwurl4", "shuqiqdbody4", "shuqijsqdbody4", "shuqisyzjurl4", "shuqitxjlbody4", "shuqicjbody5",  "shuqisprwurl5", "shuqiqdbody5", "shuqijsqdbody5", "shuqisyzjurl5", "shuqitxjlbody5", "shuqicjbody6",  "shuqisprwurl6", "shuqiqdbody6", "shuqijsqdbody6", "shuqisyzjurl6", "shuqitxjlbody6", "shuqicjbody7",  "shuqisprwurl7", "shuqiqdbody7", "shuqijsqdbody7", "shuqisyzjurl7", "shuqitxjlbody7", "shuqicjbody8",  "shuqisprwurl8", "shuqiqdbody8", "shuqijsqdbody8", "shuqisyzjurl8", "shuqitxjlbody8", "shuqicjbody9",  "shuqisprwurl9", "shuqiqdbody9", "shuqijsqdbody9", "shuqisyzjurl9", "shuqitxjlbody9", "shuqicjbody10",  "shuqisprwurl10", "shuqiqdbody10", "shuqijsqdbody10", "shuqisyzjurl10", "shuqitxjlbody10", "shuqicjbody11",  "shuqisprwurl11", "shuqiqdbody11", "shuqijsqdbody11", "shuqisyzjurl11", "shuqitxjlbody11", "shuqicjbody12",  "shuqisprwurl12", "shuqiqdbody12", "shuqijsqdbody12", "shuqisyzjurl12", "shuqitxjlbody12", "shuqicjbody13",  "shuqisprwurl13", "shuqiqdbody13", "shuqijsqdbody13", "shuqisyzjurl13", "shuqitxjlbody13", "shuqicjbody14",  "shuqisprwurl14", "shuqiqdbody14", "shuqijsqdbody14", "shuqisyzjurl14", "shuqitxjlbody14", "shuqicjbody15",  "shuqisprwurl15", "shuqiqdbody15", "shuqijsqdbody15", "shuqisyzjurl15", "shuqitxjlbody15", "shuqicjbody16",  "shuqisprwurl16", "shuqiqdbody16", "shuqijsqdbody16", "shuqisyzjurl16", "shuqitxjlbody16", "shuqicjbody17",  "shuqisprwurl17", "shuqiqdbody17", "shuqijsqdbody17", "shuqisyzjurl17", "shuqitxjlbody17", "shuqicjbody18",  "shuqisprwurl18", "shuqiqdbody18", "shuqijsqdbody18", "shuqisyzjurl18", "shuqitxjlbody18", "shuqicjbody19",  "shuqisprwurl19", "shuqiqdbody19", "shuqijsqdbody19", "shuqisyzjurl19", "shuqitxjlbody19", "shuqicjbody20",  "shuqisprwurl20", "shuqiqdbody20", "shuqijsqdbody20", "shuqisyzjurl20", "shuqitxjlbody20", "shuqicjbody21",  "shuqisprwurl21", "shuqiqdbody21", "shuqijsqdbody21", "shuqisyzjurl21", "shuqitxjlbody21", "shuqicjbody22",  "shuqisprwurl22", "shuqiqdbody22", "shuqijsqdbody22", "shuqisyzjurl22", "shuqitxjlbody22", "shuqicjbody23",  "shuqisprwurl23", "shuqiqdbody23", "shuqijsqdbody23", "shuqisyzjurl23", "shuqitxjlbody23", "shuqicjbody24",  "shuqisprwurl24", "shuqiqdbody24", "shuqijsqdbody24", "shuqisyzjurl24", "shuqitxjlbody24", "shuqicjbody25",  "shuqisprwurl25", "shuqiqdbody25", "shuqijsqdbody25", "shuqisyzjurl25", "shuqitxjlbody25", "shuqicjbody26",  "shuqisprwurl26", "shuqiqdbody26", "shuqijsqdbody26", "shuqisyzjurl26", "shuqitxjlbody26", "shuqicjbody27",  "shuqisprwurl27", "shuqiqdbody27", "shuqijsqdbody27", "shuqisyzjurl27", "shuqitxjlbody27", "shuqicjbody28",  "shuqisprwurl28", "shuqiqdbody28", "shuqijsqdbody28", "shuqisyzjurl28", "shuqitxjlbody28", "shuqicjbody29",  "shuqisprwurl29", "shuqiqdbody29", "shuqijsqdbody29", "shuqisyzjurl29", "shuqitxjlbody29", "shuqicjbody30",  "shuqisprwurl30", "shuqiqdbody30", "shuqijsqdbody30", "shuqisyzjurl30", "shuqitxjlbody30"],
        "author": "@ziye",
        "settings": [{
            "id": "shuqiSuffix",
            "name": "当前账号",
            "val": "1",
            "type": "number",
            "desc": "当前抓取ck记录的账号序号，如：1、2、3、"
        }, {
            "id": "shuqiCount",
            "name": "账号个数",
            "val": "1",
            "type": "number",
            "desc": "指定任务最多跑几个账号，根据抓取的账号数据个数来设值"
        }, {
            "id": "shuqiXH",
            "name": "循环获取CK",
            "val": "0",
            "type": "number",
            "desc": "关闭 1开启,默认关闭"
        }, {
            "id": "shuqiTX",
            "name": "提现提醒",
            "val": "100",
            "type": "number",
            "desc": "关闭 设置余额大于多少提醒"
        }, {
            "id": "shuqiXYZ",
            "name": "执行概率",
            "val": "100",
            "type": "number",
            "desc": "不执行 可设置0-100,默认百分百"
        }, {
            "id": "shuqintfst",
            "name": "推送控制",
            "val": "1",
            "type": "number",
            "desc": "关闭，1推送,默认12点以及23点推送"
        }, {
            "id": "shuqimsgst",
            "name": "通知控制",
            "val": "2",
            "type": "number",
            "desc": "关闭，1为 所有通知，2为 12，23 点通知，3为 6，12，18，23 点通知 "
        }, {
            "id": "shuqimsgm",
            "name": "推送-通知 分钟控制",
            "val": "59",
            "type": "number",
            "desc": "推送以及通知控制在什么分钟段，可设置0-59,默认0到10"
        }],
        "repo": "https://cdn.jsdelivr.net/gh/ziye888/JavaScript@main/Task/shuqi.js",
        "icons": ["https://cdn.jsdelivr.net/gh/ziye888/JavaScript@main/Task/shuqi.png", "https://cdn.jsdelivr.net/gh/ziye888/JavaScript@main/Task/shuqi.png"],
        "script": "https://cdn.jsdelivr.net/gh/ziye888/JavaScript@main/Task/shuqi.js"
    }]
}
